cryptoprice_serialization/__init__.py
cryptoprice_serialization/business_logic/__init__.py
cryptoprice_serialization/business_logic/instrument_definition.py
cryptoprice_serialization/business_logic/prices.py
cryptoprice_serialization/serializer/__init__.py
cryptoprice_serialization/serializer/serialize.py
cryptoprice_serialization/serializer/serialization/__init__.py
cryptoprice_serialization/serializer/serialization/message_pb2.py
cryptoprice_serialization-0.0.4.data/scripts/cryptoprice_deserialize
cryptoprice_serialization-0.0.4.dist-info/LICENSE
cryptoprice_serialization-0.0.4.dist-info/METADATA
cryptoprice_serialization-0.0.4.dist-info/WHEEL
cryptoprice_serialization-0.0.4.dist-info/top_level.txt
cryptoprice_serialization-0.0.4.dist-info/RECORD
