Metadata-Version: 2.1
Name: cryptoprice-serialization
Version: 0.0.4
Summary: Cryptoprice objects serialization/deserialization
Home-page: https://bitbucket.org/metagora/metagora/src/master
Author: Jozef Rudy
Author-email: jozef.rudy@gmail.com
License: UNKNOWN
Platform: UNKNOWN
Classifier: Programming Language :: Python :: 3
Classifier: License :: OSI Approved :: MIT License
Classifier: Operating System :: OS Independent
Requires-Python: >=3.6
License-File: LICENSE
